{
    "footonsat": [
        {
            "compet": "Spanish La Liga 2 - Week 33",
            "match": "     Las Palmas   vs   Granada",
            "flags": {
                "team1": "spain",
                "team2": "spain"
            },
            "time": "17:00",
            "date": "2026-04-02"
        },
        {
            "channel": "beIN Sports France 5 HD max",
            "sat": "Astra 1M 19.2\u00b0e",
            "freq": "11856 V 29700 - 2/3",
            "encry": "HD NagraVision",
            "link": "#",
            "related_to": "     Las Palmas   vs   Granada"
        },
        {
            "compet": "Spanish La Liga 2 - Week 33",
            "match": "     Castell\u00f3n   vs   Almer\u00eda",
            "flags": {
                "team1": "spain",
                "team2": "spain"
            },
            "time": "18:00",
            "date": "2026-04-02"
        },
        {
            "channel": "beIN Sports MENA 3 HD",
            "sat": "Eshail 2 25.5\u00b0e",
            "freq": "10810 H 27500 - 2/3",
            "encry": "HD Irdeto",
            "link": "#",
            "related_to": "     Castell\u00f3n   vs   Almer\u00eda"
        },
        {
            "compet": "Spanish La Liga 2 - Week 33",
            "match": "     Legan\u00e9s   vs   Real Zaragoza",
            "flags": {
                "team1": "spain",
                "team2": "spain"
            },
            "time": "19:30",
            "date": "2026-04-02"
        },
        {
            "channel": "Aragon Deporte Stream",
            "sat": "* IPTV/Stream 0.0\u00b0",
            "freq": "0000 ",
            "encry": "LiveOnSat.com",
            "link": "https://www.cartv.es/aragondeporte/directo",
            "related_to": "     Legan\u00e9s   vs   Real Zaragoza"
        },
        {
            "channel": "Arag\u00f3n TV HD",
            "sat": "*DTT 0.0\u00b0-",
            "freq": "0000 - 0",
            "encry": "FTA",
            "link": "#",
            "related_to": "     Legan\u00e9s   vs   Real Zaragoza"
        },
        {
            "channel": "GOL Espa\u00f1a HD",
            "sat": "* IPTV/Stream 0.0\u00b0",
            "freq": "0000 - -",
            "encry": "NagraVision",
            "link": "https://www.goltelevision.com/en-directo",
            "related_to": "     Legan\u00e9s   vs   Real Zaragoza"
        },
        {
            "compet": "Spanish La Liga 2 - Week 34",
            "match": "     C\u00e1diz   vs   C\u00f3rdoba",
            "flags": {
                "team1": "spain",
                "team2": "spain"
            },
            "time": "12:00",
            "date": "2026-04-04"
        },
        {
            "channel": "Premier Sports GB Player HD",
            "sat": "* IPTV/Stream 0.0\u00b0",
            "freq": "0000 0",
            "encry": "",
            "link": "https://www.premiersports.com/fr/live-now-on-demand",
            "related_to": "     C\u00e1diz   vs   C\u00f3rdoba"
        },
        {
            "compet": "Spanish La Liga 2 - Week 34",
            "match": "     Las Palmas   vs   Huesca",
            "flags": {
                "team1": "spain",
                "team2": "spain"
            },
            "time": "16:30",
            "date": "2026-04-05"
        },
        {
            "channel": "Aragon Deporte Stream",
            "sat": "* IPTV/Stream 0.0\u00b0",
            "freq": "0000 ",
            "encry": "LiveOnSat.com",
            "link": "https://www.cartv.es/aragondeporte/directo",
            "related_to": "     Las Palmas   vs   Huesca"
        },
        {
            "channel": "Arag\u00f3n TV HD",
            "sat": "*DTT 0.0\u00b0-",
            "freq": "0000 - 0",
            "encry": "FTA",
            "link": "#",
            "related_to": "     Las Palmas   vs   Huesca"
        },
        {
            "channel": "beIN Sports France 9 HD max",
            "sat": "Astra 1M 19.2\u00b0e",
            "freq": "11895 V 29700 - 2/3",
            "encry": "HD NagraVision",
            "link": "#",
            "related_to": "     Las Palmas   vs   Huesca"
        },
        {
            "channel": "GOL Espa\u00f1a HD",
            "sat": "* IPTV/Stream 0.0\u00b0",
            "freq": "0000 - -",
            "encry": "NagraVision",
            "link": "https://www.goltelevision.com/en-directo",
            "related_to": "     Las Palmas   vs   Huesca"
        },
        {
            "compet": "Spanish La Liga 2 - Week 35",
            "match": "     M\u00e1laga   vs   Las Palmas",
            "flags": {
                "team1": "spain",
                "team2": "spain"
            },
            "time": "16:30",
            "date": "2026-04-11"
        },
        {
            "channel": "Premier Sports GB Player HD",
            "sat": "* IPTV/Stream 0.0\u00b0",
            "freq": "0000 0",
            "encry": "",
            "link": "https://www.premiersports.com/fr/live-now-on-demand",
            "related_to": "     M\u00e1laga   vs   Las Palmas"
        },
        {
            "compet": "Spanish La Liga 2 - Week 35",
            "match": "     Huesca   vs   Deportivo La Coru\u00f1a",
            "flags": {
                "team1": "spain",
                "team2": "spain"
            },
            "time": "14:15",
            "date": "2026-04-12"
        },
        {
            "channel": "Aragon Deporte Stream",
            "sat": "* IPTV/Stream 0.0\u00b0",
            "freq": "0000 ",
            "encry": "LiveOnSat.com",
            "link": "https://www.cartv.es/aragondeporte/directo",
            "related_to": "     Huesca   vs   Deportivo La Coru\u00f1a"
        },
        {
            "channel": "Arag\u00f3n TV HD",
            "sat": "*DTT 0.0\u00b0-",
            "freq": "0000 - 0",
            "encry": "FTA",
            "link": "#",
            "related_to": "     Huesca   vs   Deportivo La Coru\u00f1a"
        },
        {
            "channel": "GOL Espa\u00f1a HD",
            "sat": "* IPTV/Stream 0.0\u00b0",
            "freq": "0000 - -",
            "encry": "NagraVision",
            "link": "https://www.goltelevision.com/en-directo",
            "related_to": "     Huesca   vs   Deportivo La Coru\u00f1a"
        },
        {
            "channel": "TVG Galicia",
            "sat": "*DTT 0.0\u00b0-",
            "freq": "0000 - -",
            "encry": "FTA",
            "link": "https://www.agalega.gal/videos/76475-tvg",
            "related_to": "     Huesca   vs   Deportivo La Coru\u00f1a"
        },
        {
            "compet": "Spanish La Liga 2 - Week 36",
            "match": "     Real Zaragoza   vs   Ceuta",
            "flags": {
                "team1": "spain",
                "team2": "spain"
            },
            "time": "14:15",
            "date": "2026-04-18"
        },
        {
            "channel": "Aragon Deporte Stream",
            "sat": "* IPTV/Stream 0.0\u00b0",
            "freq": "0000 ",
            "encry": "LiveOnSat.com",
            "link": "https://www.cartv.es/aragondeporte/directo",
            "related_to": "     Real Zaragoza   vs   Ceuta"
        },
        {
            "channel": "Arag\u00f3n TV HD",
            "sat": "*DTT 0.0\u00b0-",
            "freq": "0000 - 0",
            "encry": "FTA",
            "link": "#",
            "related_to": "     Real Zaragoza   vs   Ceuta"
        },
        {
            "channel": "GOL Espa\u00f1a HD",
            "sat": "* IPTV/Stream 0.0\u00b0",
            "freq": "0000 - -",
            "encry": "NagraVision",
            "link": "https://www.goltelevision.com/en-directo",
            "related_to": "     Real Zaragoza   vs   Ceuta"
        }
    ]
}